ezpda/__init__.py
ezpda/data_structure.py
ezpda/pda.py
ezpda/sas.py
ezpda/setup.py
ezpda-1.0.dist-info/METADATA
ezpda-1.0.dist-info/WHEEL
ezpda-1.0.dist-info/top_level.txt
ezpda-1.0.dist-info/RECORD
